advancepackage/__init__.py
advancepackage-0.0.0.dist-info/METADATA
advancepackage-0.0.0.dist-info/WHEEL
advancepackage-0.0.0.dist-info/license.txt
advancepackage-0.0.0.dist-info/top_level.txt
advancepackage-0.0.0.dist-info/RECORD
