Metadata-Version: 2.1
Name: advancepackage
Version: 0.0.0
Summary: This is description
Author: Aastha Giri
Author-email: giriaastha54321@gmail.com
License-File: license.txt
